setup.cfg
setup.py
python/cookbook/LICENSE
python/cookbook/README
python/cookbook/VERSION
python/cookbook/__init__.py
python/cookbook/bidirectional_map.py
python/cookbook/bunch.py
python/cookbook/cache_decorator.py
python/cookbook/console.py
python/cookbook/const.py
python/cookbook/decorate.py
python/cookbook/dicts.py
python/cookbook/enum.py
python/cookbook/equivalence.py
python/cookbook/function_as_task.py
python/cookbook/groupby.py
python/cookbook/interval.py
python/cookbook/lru_cache.py
python/cookbook/named_tuple.py
python/cookbook/output_context.py
python/cookbook/permutation.py
python/cookbook/persisted_cache.py
python/cookbook/pre_post_conditions.py
python/cookbook/process_priority.py
python/cookbook/progress.py
python/cookbook/pylab_utils.py
python/cookbook/pytables_utils.py
python/cookbook/rb_interval_tree.py
python/cookbook/rbtree.py
python/cookbook/reverse_dict.py
python/cookbook/script_basics.py
python/cookbook/simple_logging.py
python/cookbook/timer.py
python/cookbook/venn.py
python/cookbook/workflow.py
python/cookbook.egg-info/PKG-INFO
python/cookbook.egg-info/SOURCES.txt
python/cookbook.egg-info/dependency_links.txt
python/cookbook.egg-info/requires.txt
python/cookbook.egg-info/top_level.txt