Metadata-Version: 1.1
Name: cookbook
Version: 2.2.25
Summary: Some useful Python code, mainly from the Python cookbook
Home-page: http://sysbio.mrc-bsu.cam.ac.uk/johns/Cookbook/docs/build/html/
Author: John Reid
Author-email: john.reid@mrc-bsu.cam.ac.uk
License: UNKNOWN
Platform: UNKNOWN
Classifier: Development Status :: 5 - Production/Stable
Classifier: Environment :: Other Environment
Classifier: Intended Audience :: Developers
Classifier: License :: OSI Approved :: BSD License
Classifier: Operating System :: OS Independent
Classifier: Programming Language :: Python
Classifier: Topic :: Software Development :: Libraries
